{"nodes": [{"id": "c_users_vaibhav_downloads_compressed_silvoraa_final_main_pages_accountpage_tsx", "label": "AccountPage.tsx", "file_type": "code", "source_file": "C:\\Users\\Vaibhav\\Downloads\\Compressed\\silvoraa-final-main\\pages\\AccountPage.tsx", "source_location": "L1"}, {"id": "pages_accountpage_handleavatarclick", "label": "handleAvatarClick()", "file_type": "code", "source_file": "C:\\Users\\Vaibhav\\Downloads\\Compressed\\silvoraa-final-main\\pages\\AccountPage.tsx", "source_location": "L19"}, {"id": "pages_accountpage_handlefilechange", "label": "handleFileChange()", "file_type": "code", "source_file": "C:\\Users\\Vaibhav\\Downloads\\Compressed\\silvoraa-final-main\\pages\\AccountPage.tsx", "source_location": "L23"}, {"id": "pages_accountpage_handlenamesave", "label": "handleNameSave()", "file_type": "code", "source_file": "C:\\Users\\Vaibhav\\Downloads\\Compressed\\silvoraa-final-main\\pages\\AccountPage.tsx", "source_location": "L34"}, {"id": "pages_accountpage_handleaddressupdate", "label": "handleAddressUpdate()", "file_type": "code", "source_file": "C:\\Users\\Vaibhav\\Downloads\\Compressed\\silvoraa-final-main\\pages\\AccountPage.tsx", "source_location": "L41"}], "edges": [{"source": "c_users_vaibhav_downloads_compressed_silvoraa_final_main_pages_accountpage_tsx", "target": "react", "relation": "imports_from", "confidence": "EXTRACTED", "source_file": "C:\\Users\\Vaibhav\\Downloads\\Compressed\\silvoraa-final-main\\pages\\AccountPage.tsx", "source_location": "L1", "weight": 1.0}, {"source": "c_users_vaibhav_downloads_compressed_silvoraa_final_main_pages_accountpage_tsx", "target": "react_helmet_async", "relation": "imports_from", "confidence": "EXTRACTED", "source_file": "C:\\Users\\Vaibhav\\Downloads\\Compressed\\silvoraa-final-main\\pages\\AccountPage.tsx", "source_location": "L2", "weight": 1.0}, {"source": "c_users_vaibhav_downloads_compressed_silvoraa_final_main_pages_accountpage_tsx", "target": "c_users_vaibhav_downloads_compressed_silvoraa_final_main_components_auth_authcontext", "relation": "imports_from", "confidence": "EXTRACTED", "source_file": "C:\\Users\\Vaibhav\\Downloads\\Compressed\\silvoraa-final-main\\pages\\AccountPage.tsx", "source_location": "L3", "weight": 1.0}, {"source": "c_users_vaibhav_downloads_compressed_silvoraa_final_main_pages_accountpage_tsx", "target": "lucide_react", "relation": "imports_from", "confidence": "EXTRACTED", "source_file": "C:\\Users\\Vaibhav\\Downloads\\Compressed\\silvoraa-final-main\\pages\\AccountPage.tsx", "source_location": "L4", "weight": 1.0}, {"source": "c_users_vaibhav_downloads_compressed_silvoraa_final_main_pages_accountpage_tsx", "target": "react_router_dom", "relation": "imports_from", "confidence": "EXTRACTED", "source_file": "C:\\Users\\Vaibhav\\Downloads\\Compressed\\silvoraa-final-main\\pages\\AccountPage.tsx", "source_location": "L5", "weight": 1.0}, {"source": "c_users_vaibhav_downloads_compressed_silvoraa_final_main_pages_accountpage_tsx", "target": "pages_accountpage_handleavatarclick", "relation": "contains", "confidence": "EXTRACTED", "source_file": "C:\\Users\\Vaibhav\\Downloads\\Compressed\\silvoraa-final-main\\pages\\AccountPage.tsx", "source_location": "L19", "weight": 1.0}, {"source": "c_users_vaibhav_downloads_compressed_silvoraa_final_main_pages_accountpage_tsx", "target": "pages_accountpage_handlefilechange", "relation": "contains", "confidence": "EXTRACTED", "source_file": "C:\\Users\\Vaibhav\\Downloads\\Compressed\\silvoraa-final-main\\pages\\AccountPage.tsx", "source_location": "L23", "weight": 1.0}, {"source": "c_users_vaibhav_downloads_compressed_silvoraa_final_main_pages_accountpage_tsx", "target": "pages_accountpage_handlenamesave", "relation": "contains", "confidence": "EXTRACTED", "source_file": "C:\\Users\\Vaibhav\\Downloads\\Compressed\\silvoraa-final-main\\pages\\AccountPage.tsx", "source_location": "L34", "weight": 1.0}, {"source": "c_users_vaibhav_downloads_compressed_silvoraa_final_main_pages_accountpage_tsx", "target": "pages_accountpage_handleaddressupdate", "relation": "contains", "confidence": "EXTRACTED", "source_file": "C:\\Users\\Vaibhav\\Downloads\\Compressed\\silvoraa-final-main\\pages\\AccountPage.tsx", "source_location": "L41", "weight": 1.0}], "raw_calls": [{"caller_nid": "pages_accountpage_handleavatarclick", "callee": "click", "is_member_call": true, "source_file": "C:\\Users\\Vaibhav\\Downloads\\Compressed\\silvoraa-final-main\\pages\\AccountPage.tsx", "source_location": "L20"}, {"caller_nid": "pages_accountpage_handlefilechange", "callee": "readAsDataURL", "is_member_call": true, "source_file": "C:\\Users\\Vaibhav\\Downloads\\Compressed\\silvoraa-final-main\\pages\\AccountPage.tsx", "source_location": "L30"}, {"caller_nid": "pages_accountpage_handlenamesave", "callee": "trim", "is_member_call": true, "source_file": "C:\\Users\\Vaibhav\\Downloads\\Compressed\\silvoraa-final-main\\pages\\AccountPage.tsx", "source_location": "L35"}, {"caller_nid": "pages_accountpage_handlenamesave", "callee": "updateProfile", "is_member_call": false, "source_file": "C:\\Users\\Vaibhav\\Downloads\\Compressed\\silvoraa-final-main\\pages\\AccountPage.tsx", "source_location": "L36"}, {"caller_nid": "pages_accountpage_handlenamesave", "callee": "setIsEditingName", "is_member_call": false, "source_file": "C:\\Users\\Vaibhav\\Downloads\\Compressed\\silvoraa-final-main\\pages\\AccountPage.tsx", "source_location": "L38"}, {"caller_nid": "pages_accountpage_handleaddressupdate", "callee": "updateProfile", "is_member_call": false, "source_file": "C:\\Users\\Vaibhav\\Downloads\\Compressed\\silvoraa-final-main\\pages\\AccountPage.tsx", "source_location": "L42"}]}